jupyter_workflow/__init__.py
jupyter_workflow/version.py
jupyter_workflow/config/__init__.py
jupyter_workflow/config/validator.py
jupyter_workflow/config/schemas/v1.0/config_schema.json
jupyter_workflow/config/schemas/v1.0/docker-compose.json
jupyter_workflow/config/schemas/v1.0/docker.json
jupyter_workflow/config/schemas/v1.0/helm2.json
jupyter_workflow/config/schemas/v1.0/helm3.json
jupyter_workflow/config/schemas/v1.0/occam.json
jupyter_workflow/config/schemas/v1.0/queue_manager.json
jupyter_workflow/config/schemas/v1.0/singularity.json
jupyter_workflow/config/schemas/v1.0/ssh.json
jupyter_workflow/ipython/__init__.py
jupyter_workflow/ipython/__main__.py
jupyter_workflow/ipython/install.py
jupyter_workflow/ipython/ipkernel.py
jupyter_workflow/ipython/shell.py
jupyter_workflow/ipython/kernelspec/kernel.js
jupyter_workflow/streamflow/__init__.py
jupyter_workflow/streamflow/combinator.py
jupyter_workflow/streamflow/command.py
jupyter_workflow/streamflow/executor.py
jupyter_workflow/streamflow/token_processor.py
jupyter_workflow/streamflow/translator.py
jupyter_workflow-0.0.37.dist-info/LICENSE
jupyter_workflow-0.0.37.dist-info/METADATA
jupyter_workflow-0.0.37.dist-info/WHEEL
jupyter_workflow-0.0.37.dist-info/top_level.txt
jupyter_workflow-0.0.37.dist-info/RECORD
