Metadata-Version: 2.1
Name: jupyter-workflow
Version: 0.0.37
Summary: Jupyter Workflow Kernel
Home-page: https://github.com/alpha-unito/jupyter-workflow
Author: Iacopo Colonnelli
Author-email: iacopo.colonnelli@unito.it
License: LGPLv3
Download-URL: https://github.com/alpha-unito/jupyter-workflow/releases
Platform: UNKNOWN
Classifier: Development Status :: 3 - Alpha
Classifier: License :: OSI Approved :: GNU Lesser General Public License v3 (LGPLv3)
Classifier: Intended Audience :: Developers
Classifier: Intended Audience :: Science/Research
Classifier: Operating System :: MacOS :: MacOS X
Classifier: Operating System :: POSIX
Classifier: Programming Language :: Python :: 3.8
Classifier: Topic :: Scientific/Engineering
Classifier: Topic :: System :: Distributed Computing
Requires-Python: >=3.8, <4
License-File: LICENSE
Requires-Dist: dill
Requires-Dist: IPython
Requires-Dist: ipython-genutils
Requires-Dist: ipykernel
Requires-Dist: jsonref
Requires-Dist: jsonschema
Requires-Dist: jupyter-client
Requires-Dist: streamflow (>=0.0.30)
Requires-Dist: traitlets
